file_iter/__init__.py
file_iter/file_iter.py
file_iter/py.typed
file_iter-0.1.3.dist-info/LICENSE
file_iter-0.1.3.dist-info/METADATA
file_iter-0.1.3.dist-info/WHEEL
file_iter-0.1.3.dist-info/RECORD
