Metadata-Version: 2.1
Name: file_iter
Version: 0.1.3
Summary: A Swiss Army knife iterator for files (or any iterator of strings)
Home-page: https://github.com/jevandezande/file_iter
License: MIT
Author: Jonathon Vandezande
Requires-Python: >=3.12
Classifier: License :: OSI Approved :: MIT License
Classifier: Programming Language :: Python :: 3
Classifier: Programming Language :: Python :: 3.12
Project-URL: Repository, https://github.com/jevandezande/file_iter
